ironpdf-2025.12.1.4.data/data/IronPdf.Slim/BitMiracle.LibTiff.NET.dll
ironpdf-2025.12.1.4.data/data/IronPdf.Slim/Google.Protobuf.dll
ironpdf-2025.12.1.4.data/data/IronPdf.Slim/Grpc.Core.Api.dll
ironpdf-2025.12.1.4.data/data/IronPdf.Slim/Grpc.Core.dll
ironpdf-2025.12.1.4.data/data/IronPdf.Slim/Grpc.Net.Client.dll
ironpdf-2025.12.1.4.data/data/IronPdf.Slim/Grpc.Net.Common.dll
ironpdf-2025.12.1.4.data/data/IronPdf.Slim/IronPdf.dll
ironpdf-2025.12.1.4.data/data/IronPdf.Slim/IronSoftware.Abstractions.dll
ironpdf-2025.12.1.4.data/data/IronPdf.Slim/IronSoftware.Drawing.Abstractions.dll
ironpdf-2025.12.1.4.data/data/IronPdf.Slim/IronSoftware.Drawing.Common.dll
ironpdf-2025.12.1.4.data/data/IronPdf.Slim/IronSoftware.Logger.dll
ironpdf-2025.12.1.4.data/data/IronPdf.Slim/IronSoftware.Shared.dll
ironpdf-2025.12.1.4.data/data/IronPdf.Slim/Microsoft.Extensions.Configuration.Abstractions.dll
ironpdf-2025.12.1.4.data/data/IronPdf.Slim/Microsoft.Extensions.Configuration.Binder.dll
ironpdf-2025.12.1.4.data/data/IronPdf.Slim/Microsoft.Extensions.Configuration.FileExtensions.dll
ironpdf-2025.12.1.4.data/data/IronPdf.Slim/Microsoft.Extensions.Configuration.Json.dll
ironpdf-2025.12.1.4.data/data/IronPdf.Slim/Microsoft.Extensions.Configuration.dll
ironpdf-2025.12.1.4.data/data/IronPdf.Slim/Microsoft.Extensions.FileProviders.Abstractions.dll
ironpdf-2025.12.1.4.data/data/IronPdf.Slim/Microsoft.Extensions.FileProviders.Physical.dll
ironpdf-2025.12.1.4.data/data/IronPdf.Slim/Microsoft.Extensions.FileSystemGlobbing.dll
ironpdf-2025.12.1.4.data/data/IronPdf.Slim/Microsoft.Extensions.Logging.Abstractions.dll
ironpdf-2025.12.1.4.data/data/IronPdf.Slim/Microsoft.Extensions.Primitives.dll
ironpdf-2025.12.1.4.data/data/IronPdf.Slim/Microsoft.Maui.Graphics.dll
ironpdf-2025.12.1.4.data/data/IronPdf.Slim/Microsoft.Maui.Graphics.xml
ironpdf-2025.12.1.4.data/data/IronPdf.Slim/Pkcs11Interop.dll
ironpdf-2025.12.1.4.data/data/IronPdf.Slim/Polly.Core.dll
ironpdf-2025.12.1.4.dist-info/METADATA
ironpdf-2025.12.1.4.dist-info/WHEEL
ironpdf-2025.12.1.4.dist-info/top_level.txt
ironpdf-2025.12.1.4.dist-info/RECORD
